zfit/__init__.py
zfit/_interfaces.py
zfit/_version.py
zfit/binned.py
zfit/constraint.py
zfit/data.py
zfit/dill.py
zfit/dimension.py
zfit/exception.py
zfit/func.py
zfit/hs3.py
zfit/interface.py
zfit/loss.py
zfit/minimize.py
zfit/param.py
zfit/pdf.py
zfit/plot.py
zfit/result.py
zfit/sample.py
zfit/settings.py
zfit/_data/__init__.py
zfit/_data/binneddatav1.py
zfit/_data/unbinneddata.py
zfit/_loss/__init__.py
zfit/_loss/binnedloss.py
zfit/_variables/__init__.py
zfit/_variables/axis.py
zfit/_variables/varsupport.py
zfit/core/__init__.py
zfit/core/basefunc.py
zfit/core/basemodel.py
zfit/core/baseobject.py
zfit/core/basepdf.py
zfit/core/binnedpdf.py
zfit/core/binning.py
zfit/core/constraint.py
zfit/core/coordinates.py
zfit/core/data.py
zfit/core/dimension.py
zfit/core/func.py
zfit/core/integration.py
zfit/core/loss.py
zfit/core/operations.py
zfit/core/parameter.py
zfit/core/pdf.py
zfit/core/sample.py
zfit/core/serialmixin.py
zfit/core/space.py
zfit/core/tensorlike.py
zfit/core/testing.py
zfit/core/values.py
zfit/minimizers/__init__.py
zfit/minimizers/base_tf.py
zfit/minimizers/baseminimizer.py
zfit/minimizers/errors.py
zfit/minimizers/evaluation.py
zfit/minimizers/fitresult.py
zfit/minimizers/interface.py
zfit/minimizers/ipopt.py
zfit/minimizers/minimizer_lm.py
zfit/minimizers/minimizer_minuit.py
zfit/minimizers/minimizer_nlopt.py
zfit/minimizers/minimizer_tfp.py
zfit/minimizers/minimizers_scipy.py
zfit/minimizers/optimizers_tf.py
zfit/minimizers/strategy.py
zfit/minimizers/termination.py
zfit/models/__init__.py
zfit/models/basefunctor.py
zfit/models/basic.py
zfit/models/binned_functor.py
zfit/models/cache.py
zfit/models/conditional.py
zfit/models/convolution.py
zfit/models/dist_tfp.py
zfit/models/functions.py
zfit/models/functor.py
zfit/models/histmodifier.py
zfit/models/histogram.py
zfit/models/interpolation.py
zfit/models/kde.py
zfit/models/morphing.py
zfit/models/physics.py
zfit/models/polynomials.py
zfit/models/postprocess.py
zfit/models/special.py
zfit-0.27.1.dist-info/METADATA
zfit-0.27.1.dist-info/WHEEL
zfit-0.27.1.dist-info/licenses/AUTHORS.rst
zfit-0.27.1.dist-info/licenses/LICENSE
zfit-0.27.1.dist-info/RECORD
