Metadata-Version: 2.4
Name: zfit
Version: 0.27.1
Summary: scalable pythonic model fitting for high energy physics
Project-URL: Homepage, https://github.com/zfit/zfit
Author-email: Jonas Eschle <Jonas.Eschle@cern.ch>, Albert Puig <apuignav@gmail.com>, Rafael Silva Coutinho <rsilvaco@cern.ch>, Matthieu Marinangeli <matthieu.marinangeli@cern.ch>
Maintainer-email: zfit <zfit@physik.uzh.ch>
License: BSD-3-Clause
License-File: AUTHORS.rst
License-File: LICENSE
Keywords: HEP,TensorFlow,fitting,likelihood,model,scalable
Classifier: Development Status :: 4 - Beta
Classifier: Intended Audience :: Science/Research
Classifier: Natural Language :: English
Classifier: Operating System :: MacOS
Classifier: Operating System :: Microsoft :: Windows
Classifier: Operating System :: Unix
Classifier: Programming Language :: Python :: 3
Classifier: Programming Language :: Python :: 3 :: Only
Classifier: Programming Language :: Python :: 3.10
Classifier: Programming Language :: Python :: 3.11
Classifier: Programming Language :: Python :: 3.12
Classifier: Topic :: Scientific/Engineering :: Physics
Requires-Python: <3.13,>=3.10
Requires-Dist: attrs
Requires-Dist: boost-histogram
Requires-Dist: colorama
Requires-Dist: colored
Requires-Dist: colorlog
Requires-Dist: deprecated
Requires-Dist: dill
Requires-Dist: dotmap
Requires-Dist: frozendict
Requires-Dist: hist
Requires-Dist: iminuit>=2.3
Requires-Dist: jacobi
Requires-Dist: numdifftools
Requires-Dist: numpy>=1.16
Requires-Dist: ordered-set
Requires-Dist: pandas
Requires-Dist: pydantic>=2.0.0
Requires-Dist: pyyaml
Requires-Dist: scipy>=1.2
Requires-Dist: tabulate
Requires-Dist: tensorflow-probability[tf]<0.27,>=0.24
Requires-Dist: tensorflow<2.20,>=2.16.2
Requires-Dist: texttable
Requires-Dist: uhi
Requires-Dist: uproot>=4
Requires-Dist: xxhash
Requires-Dist: zfit-interface
Provides-Extra: all
Requires-Dist: asdf<4.0.0; extra == 'all'
Requires-Dist: awkward-pandas; extra == 'all'
Requires-Dist: ipyopt>=0.12; (sys_platform == 'linux') and extra == 'all'
Requires-Dist: matplotlib; extra == 'all'
Requires-Dist: mplhep; extra == 'all'
Requires-Dist: nlopt>=2.7.1; (sys_platform == 'linux' or sys_platform == 'darwin' and platform_machine != 'arm64' or sys_platform == 'win32') and extra == 'all'
Provides-Extra: alldev
Requires-Dist: asdf<4.0.0; extra == 'alldev'
Requires-Dist: awkward-pandas; extra == 'alldev'
Requires-Dist: coverage-lcov; extra == 'alldev'
Requires-Dist: coverage>=4.5.1; extra == 'alldev'
Requires-Dist: ipyopt>=0.12; (sys_platform == 'linux') and extra == 'alldev'
Requires-Dist: jax; (sys_platform != 'win32') and extra == 'alldev'
Requires-Dist: jaxlib; (sys_platform != 'win32') and extra == 'alldev'
Requires-Dist: jinja2; extra == 'alldev'
Requires-Dist: jupyter-sphinx; extra == 'alldev'
Requires-Dist: matplotlib; extra == 'alldev'
Requires-Dist: mplhep; extra == 'alldev'
Requires-Dist: myst-nb; extra == 'alldev'
Requires-Dist: nlopt>=2.7.1; (sys_platform == 'linux' or sys_platform == 'darwin' and platform_machine != 'arm64' or sys_platform == 'win32') and extra == 'alldev'
Requires-Dist: numba-stats; extra == 'alldev'
Requires-Dist: pip>=9.0.1; extra == 'alldev'
Requires-Dist: pre-commit; extra == 'alldev'
Requires-Dist: pydata-sphinx-theme>=0.9; extra == 'alldev'
Requires-Dist: pygit2; extra == 'alldev'
Requires-Dist: pyhf>=0.7.0; extra == 'alldev'
Requires-Dist: pytest-benchmark; extra == 'alldev'
Requires-Dist: pytest-cases; extra == 'alldev'
Requires-Dist: pytest-helpers-namespace; extra == 'alldev'
Requires-Dist: pytest-ordering; extra == 'alldev'
Requires-Dist: pytest-randomly; extra == 'alldev'
Requires-Dist: pytest-rerunfailures>=6; extra == 'alldev'
Requires-Dist: pytest-runner>=2.11.1; extra == 'alldev'
Requires-Dist: pytest-timeout>=1; extra == 'alldev'
Requires-Dist: pytest-xdist; extra == 'alldev'
Requires-Dist: pytest>=3.4.2; extra == 'alldev'
Requires-Dist: pyyaml; extra == 'alldev'
Requires-Dist: ray; extra == 'alldev'
Requires-Dist: scikit-hep-testdata; extra == 'alldev'
Requires-Dist: setupext-janitor; extra == 'alldev'
Requires-Dist: sphinx-autodoc-typehints; extra == 'alldev'
Requires-Dist: sphinx-copybutton; extra == 'alldev'
Requires-Dist: sphinx-panels; extra == 'alldev'
Requires-Dist: sphinx-togglebutton; extra == 'alldev'
Requires-Dist: sphinx>=5.0.0; extra == 'alldev'
Requires-Dist: sphinxcontrib-applehelp>1.0.8; extra == 'alldev'
Requires-Dist: sphinxcontrib-bibtex; extra == 'alldev'
Requires-Dist: sphinxcontrib-youtube>=1.0.0; extra == 'alldev'
Requires-Dist: tqdm; extra == 'alldev'
Requires-Dist: twine>=1.10.0; extra == 'alldev'
Requires-Dist: wheel>=0.29.0; extra == 'alldev'
Requires-Dist: zfit-physics>=0.6.0; extra == 'alldev'
Provides-Extra: dev
Requires-Dist: asdf<4.0.0; extra == 'dev'
Requires-Dist: awkward-pandas; extra == 'dev'
Requires-Dist: coverage-lcov; extra == 'dev'
Requires-Dist: coverage>=4.5.1; extra == 'dev'
Requires-Dist: ipyopt>=0.12; (sys_platform == 'linux') and extra == 'dev'
Requires-Dist: jax; (sys_platform != 'win32') and extra == 'dev'
Requires-Dist: jaxlib; (sys_platform != 'win32') and extra == 'dev'
Requires-Dist: jinja2; extra == 'dev'
Requires-Dist: jupyter-sphinx; extra == 'dev'
Requires-Dist: matplotlib; extra == 'dev'
Requires-Dist: mplhep; extra == 'dev'
Requires-Dist: myst-nb; extra == 'dev'
Requires-Dist: nlopt>=2.7.1; (sys_platform == 'linux' or sys_platform == 'darwin' and platform_machine != 'arm64' or sys_platform == 'win32') and extra == 'dev'
Requires-Dist: numba-stats; extra == 'dev'
Requires-Dist: pip>=9.0.1; extra == 'dev'
Requires-Dist: pre-commit; extra == 'dev'
Requires-Dist: pydata-sphinx-theme>=0.9; extra == 'dev'
Requires-Dist: pygit2; extra == 'dev'
Requires-Dist: pyhf>=0.7.0; extra == 'dev'
Requires-Dist: pytest-benchmark; extra == 'dev'
Requires-Dist: pytest-cases; extra == 'dev'
Requires-Dist: pytest-helpers-namespace; extra == 'dev'
Requires-Dist: pytest-ordering; extra == 'dev'
Requires-Dist: pytest-randomly; extra == 'dev'
Requires-Dist: pytest-rerunfailures>=6; extra == 'dev'
Requires-Dist: pytest-runner>=2.11.1; extra == 'dev'
Requires-Dist: pytest-timeout>=1; extra == 'dev'
Requires-Dist: pytest-xdist; extra == 'dev'
Requires-Dist: pytest>=3.4.2; extra == 'dev'
Requires-Dist: pyyaml; extra == 'dev'
Requires-Dist: ray; extra == 'dev'
Requires-Dist: scikit-hep-testdata; extra == 'dev'
Requires-Dist: setupext-janitor; extra == 'dev'
Requires-Dist: sphinx-autodoc-typehints; extra == 'dev'
Requires-Dist: sphinx-copybutton; extra == 'dev'
Requires-Dist: sphinx-panels; extra == 'dev'
Requires-Dist: sphinx-togglebutton; extra == 'dev'
Requires-Dist: sphinx>=5.0.0; extra == 'dev'
Requires-Dist: sphinxcontrib-applehelp>1.0.8; extra == 'dev'
Requires-Dist: sphinxcontrib-bibtex; extra == 'dev'
Requires-Dist: sphinxcontrib-youtube>=1.0.0; extra == 'dev'
Requires-Dist: tqdm; extra == 'dev'
Requires-Dist: twine>=1.10.0; extra == 'dev'
Requires-Dist: wheel>=0.29.0; extra == 'dev'
Requires-Dist: zfit-physics>=0.6.0; extra == 'dev'
Provides-Extra: doc
Requires-Dist: asdf<4.0.0; extra == 'doc'
Requires-Dist: awkward-pandas; extra == 'doc'
Requires-Dist: ipyopt>=0.12; (sys_platform == 'linux') and extra == 'doc'
Requires-Dist: jinja2; extra == 'doc'
Requires-Dist: jupyter-sphinx; extra == 'doc'
Requires-Dist: matplotlib; extra == 'doc'
Requires-Dist: mplhep; extra == 'doc'
Requires-Dist: myst-nb; extra == 'doc'
Requires-Dist: nlopt>=2.7.1; (sys_platform == 'linux' or sys_platform == 'darwin' and platform_machine != 'arm64' or sys_platform == 'win32') and extra == 'doc'
Requires-Dist: pydata-sphinx-theme>=0.9; extra == 'doc'
Requires-Dist: pygit2; extra == 'doc'
Requires-Dist: ray; extra == 'doc'
Requires-Dist: sphinx-autodoc-typehints; extra == 'doc'
Requires-Dist: sphinx-copybutton; extra == 'doc'
Requires-Dist: sphinx-panels; extra == 'doc'
Requires-Dist: sphinx-togglebutton; extra == 'doc'
Requires-Dist: sphinx>=5.0.0; extra == 'doc'
Requires-Dist: sphinxcontrib-applehelp>1.0.8; extra == 'doc'
Requires-Dist: sphinxcontrib-bibtex; extra == 'doc'
Requires-Dist: sphinxcontrib-youtube>=1.0.0; extra == 'doc'
Requires-Dist: tqdm; extra == 'doc'
Requires-Dist: zfit-physics>=0.6.0; extra == 'doc'
Provides-Extra: docs
Requires-Dist: asdf<4.0.0; extra == 'docs'
Requires-Dist: awkward-pandas; extra == 'docs'
Requires-Dist: ipyopt>=0.12; (sys_platform == 'linux') and extra == 'docs'
Requires-Dist: jinja2; extra == 'docs'
Requires-Dist: jupyter-sphinx; extra == 'docs'
Requires-Dist: matplotlib; extra == 'docs'
Requires-Dist: mplhep; extra == 'docs'
Requires-Dist: myst-nb; extra == 'docs'
Requires-Dist: nlopt>=2.7.1; (sys_platform == 'linux' or sys_platform == 'darwin' and platform_machine != 'arm64' or sys_platform == 'win32') and extra == 'docs'
Requires-Dist: pydata-sphinx-theme>=0.9; extra == 'docs'
Requires-Dist: pygit2; extra == 'docs'
Requires-Dist: ray; extra == 'docs'
Requires-Dist: sphinx-autodoc-typehints; extra == 'docs'
Requires-Dist: sphinx-copybutton; extra == 'docs'
Requires-Dist: sphinx-panels; extra == 'docs'
Requires-Dist: sphinx-togglebutton; extra == 'docs'
Requires-Dist: sphinx>=5.0.0; extra == 'docs'
Requires-Dist: sphinxcontrib-applehelp>1.0.8; extra == 'docs'
Requires-Dist: sphinxcontrib-bibtex; extra == 'docs'
Requires-Dist: sphinxcontrib-youtube>=1.0.0; extra == 'docs'
Requires-Dist: tqdm; extra == 'docs'
Requires-Dist: zfit-physics>=0.6.0; extra == 'docs'
Provides-Extra: hs3
Requires-Dist: asdf<4.0.0; extra == 'hs3'
Provides-Extra: ipyopt
Requires-Dist: ipyopt>=0.12; (sys_platform == 'linux') and extra == 'ipyopt'
Provides-Extra: nlopt
Requires-Dist: nlopt>=2.7.1; (sys_platform == 'linux' or sys_platform == 'darwin' and platform_machine != 'arm64' or sys_platform == 'win32') and extra == 'nlopt'
Provides-Extra: plot
Requires-Dist: matplotlib; extra == 'plot'
Requires-Dist: mplhep; extra == 'plot'
Provides-Extra: test
Requires-Dist: asdf<4.0.0; extra == 'test'
Requires-Dist: awkward-pandas; extra == 'test'
Requires-Dist: coverage-lcov; extra == 'test'
Requires-Dist: coverage>=4.5.1; extra == 'test'
Requires-Dist: ipyopt>=0.12; (sys_platform == 'linux') and extra == 'test'
Requires-Dist: jax; (sys_platform != 'win32') and extra == 'test'
Requires-Dist: jaxlib; (sys_platform != 'win32') and extra == 'test'
Requires-Dist: matplotlib; extra == 'test'
Requires-Dist: mplhep; extra == 'test'
Requires-Dist: nlopt>=2.7.1; (sys_platform == 'linux' or sys_platform == 'darwin' and platform_machine != 'arm64' or sys_platform == 'win32') and extra == 'test'
Requires-Dist: numba-stats; extra == 'test'
Requires-Dist: pyhf>=0.7.0; extra == 'test'
Requires-Dist: pytest-benchmark; extra == 'test'
Requires-Dist: pytest-cases; extra == 'test'
Requires-Dist: pytest-helpers-namespace; extra == 'test'
Requires-Dist: pytest-ordering; extra == 'test'
Requires-Dist: pytest-randomly; extra == 'test'
Requires-Dist: pytest-rerunfailures>=6; extra == 'test'
Requires-Dist: pytest-runner>=2.11.1; extra == 'test'
Requires-Dist: pytest-timeout>=1; extra == 'test'
Requires-Dist: pytest-xdist; extra == 'test'
Requires-Dist: pytest>=3.4.2; extra == 'test'
Requires-Dist: pyyaml; extra == 'test'
Requires-Dist: scikit-hep-testdata; extra == 'test'
Provides-Extra: tests
Requires-Dist: asdf<4.0.0; extra == 'tests'
Requires-Dist: awkward-pandas; extra == 'tests'
Requires-Dist: coverage-lcov; extra == 'tests'
Requires-Dist: coverage>=4.5.1; extra == 'tests'
Requires-Dist: ipyopt>=0.12; (sys_platform == 'linux') and extra == 'tests'
Requires-Dist: jax; (sys_platform != 'win32') and extra == 'tests'
Requires-Dist: jaxlib; (sys_platform != 'win32') and extra == 'tests'
Requires-Dist: matplotlib; extra == 'tests'
Requires-Dist: mplhep; extra == 'tests'
Requires-Dist: nlopt>=2.7.1; (sys_platform == 'linux' or sys_platform == 'darwin' and platform_machine != 'arm64' or sys_platform == 'win32') and extra == 'tests'
Requires-Dist: numba-stats; extra == 'tests'
Requires-Dist: pyhf>=0.7.0; extra == 'tests'
Requires-Dist: pytest-benchmark; extra == 'tests'
Requires-Dist: pytest-cases; extra == 'tests'
Requires-Dist: pytest-helpers-namespace; extra == 'tests'
Requires-Dist: pytest-ordering; extra == 'tests'
Requires-Dist: pytest-randomly; extra == 'tests'
Requires-Dist: pytest-rerunfailures>=6; extra == 'tests'
Requires-Dist: pytest-runner>=2.11.1; extra == 'tests'
Requires-Dist: pytest-timeout>=1; extra == 'tests'
Requires-Dist: pytest-xdist; extra == 'tests'
Requires-Dist: pytest>=3.4.2; extra == 'tests'
Requires-Dist: pyyaml; extra == 'tests'
Requires-Dist: scikit-hep-testdata; extra == 'tests'
Provides-Extra: uproot
Requires-Dist: awkward-pandas; extra == 'uproot'
